molcloud/__init__.py
molcloud/lib.py
molcloud/main.py
molcloud/rna.py
molcloud/version.py
molcloud-0.3.0.dist-info/LICENSE
molcloud-0.3.0.dist-info/METADATA
molcloud-0.3.0.dist-info/WHEEL
molcloud-0.3.0.dist-info/entry_points.txt
molcloud-0.3.0.dist-info/top_level.txt
molcloud-0.3.0.dist-info/RECORD
