Metadata-Version: 2.1
Name: molcloud
Version: 0.3.0
Summary: Insert SVGs into matplotlib figures
Home-page: https://github.com/whitead/molcloud
Author: Andrew White
Author-email: andrew.white@rochester.edu
License: MIT
Classifier: Programming Language :: Python :: 3
Classifier: License :: OSI Approved :: MIT License
Classifier: Operating System :: OS Independent
Classifier: Framework :: Matplotlib
License-File: LICENSE
Requires-Dist: networkx
Requires-Dist: matplotlib
Requires-Dist: pandas
Requires-Dist: pygraphviz
Requires-Dist: rdkit
Requires-Dist: click
Requires-Dist: tqdm
Provides-Extra: all
Requires-Dist: numpy ; extra == 'all'
Requires-Dist: forgi (==2.0.2) ; extra == 'all'
Requires-Dist: moviepy ; extra == 'all'
Provides-Extra: rna
Requires-Dist: numpy ; extra == 'rna'
Requires-Dist: forgi (==2.0.2) ; extra == 'rna'
